wags_tails/__init__.py
wags_tails/base_source.py
wags_tails/chembl.py
wags_tails/chemidplus.py
wags_tails/cli.py
wags_tails/custom.py
wags_tails/do.py
wags_tails/drugbank.py
wags_tails/drugsatfda.py
wags_tails/ensembl.py
wags_tails/ensembl_transcript_mappings.py
wags_tails/guide_to_pharmacology.py
wags_tails/hemonc.py
wags_tails/hgnc.py
wags_tails/hpo.py
wags_tails/logging.py
wags_tails/moa.py
wags_tails/mondo.py
wags_tails/ncbi.py
wags_tails/ncbi_lrg_refseqgene.py
wags_tails/ncbi_mane.py
wags_tails/ncit.py
wags_tails/oncotree.py
wags_tails/rxnorm.py
wags_tails/utils/__init__.py
wags_tails/utils/downloads.py
wags_tails/utils/storage.py
wags_tails/utils/versioning.py
wags_tails-0.4.0.dist-info/licenses/LICENSE
wags_tails-0.4.0.dist-info/METADATA
wags_tails-0.4.0.dist-info/WHEEL
wags_tails-0.4.0.dist-info/entry_points.txt
wags_tails-0.4.0.dist-info/top_level.txt
wags_tails-0.4.0.dist-info/RECORD
