Metadata-Version: 2.4
Name: wags_tails
Version: 0.4.0
Summary: Data acquisition tools for Wagnerds
Author: Kori Kuzma, James S Stevenson, Alex H Wagner
License: MIT License
Project-URL: Homepage, https://github.com/GenomicMedLab/wags-tails/
Project-URL: Documentation, https://wags-tails.readthedocs.io/
Project-URL: Changelog, https://github.com/GenomicMedLab/wags-tails/releases
Project-URL: Source, https://github.com/GenomicMedLab/wags-tails/
Project-URL: Bug Tracker, https://github.com/GenomicMedLab/wags-tails/issues
Classifier: Development Status :: 3 - Alpha
Classifier: Framework :: Pydantic
Classifier: Framework :: Pydantic :: 2
Classifier: Intended Audience :: Science/Research
Classifier: Intended Audience :: Developers
Classifier: Topic :: Scientific/Engineering :: Bio-Informatics
Classifier: License :: OSI Approved :: MIT License
Classifier: Programming Language :: Python :: 3
Classifier: Programming Language :: Python :: 3.11
Classifier: Programming Language :: Python :: 3.12
Classifier: Programming Language :: Python :: 3.13
Requires-Python: >=3.11
License-File: LICENSE
Requires-Dist: requests
Requires-Dist: tqdm
Requires-Dist: click
Provides-Extra: tests
Requires-Dist: pytest>=6.0; extra == "tests"
Requires-Dist: pytest-cov; extra == "tests"
Requires-Dist: requests-mock; extra == "tests"
Provides-Extra: dev
Requires-Dist: pre-commit>=4.2.0; extra == "dev"
Requires-Dist: ruff==0.12.1; extra == "dev"
Provides-Extra: docs
Requires-Dist: sphinx==6.1.3; extra == "docs"
Requires-Dist: sphinx-autodoc-typehints==1.22.0; extra == "docs"
Requires-Dist: sphinx-autobuild==2021.3.14; extra == "docs"
Requires-Dist: sphinx-copybutton==0.5.2; extra == "docs"
Requires-Dist: sphinxext-opengraph==0.8.2; extra == "docs"
Requires-Dist: furo==2023.3.27; extra == "docs"
Requires-Dist: sphinx-click==5.0.1; extra == "docs"
Requires-Dist: sphinx-github-changelog==1.2.1; extra == "docs"
Dynamic: license-file
